bugswarm_cfg/__init__.py
bugswarm_cfg/javaparser.sh
bugswarm_cfg/main.py
bugswarm_cfg/soot.sh
bugswarm_cfg/spoon.sh
bugswarm_cfg-0.9.0.dist-info/LICENSE
bugswarm_cfg-0.9.0.dist-info/METADATA
bugswarm_cfg-0.9.0.dist-info/WHEEL
bugswarm_cfg-0.9.0.dist-info/entry_points.txt
bugswarm_cfg-0.9.0.dist-info/top_level.txt
bugswarm_cfg-0.9.0.dist-info/RECORD
