Metadata-Version: 2.1
Name: bugswarm-cfg
Version: 0.9.0
Summary: A tool to run BugSwarm Docker containers with sandbox environments for CFG generation using various tools.
Home-page: https://github.com/apratimshukla6/bugswarm-cfg
Author: Apratim Shukla
Author-email: apratimshukla6@gmail.com
License: MIT
Keywords: bugswarm cfg
License-File: LICENSE
Requires-Dist: beautifulsoup4
Requires-Dist: requests
